CHANGELOG.md
LICENSE
README.md
cppcheck_codequality/__init__.py
cppcheck_codequality/__main__.py
cppcheck_codequality-1.5.0.dist-info/LICENSE
cppcheck_codequality-1.5.0.dist-info/METADATA
cppcheck_codequality-1.5.0.dist-info/WHEEL
cppcheck_codequality-1.5.0.dist-info/entry_points.txt
cppcheck_codequality-1.5.0.dist-info/RECORD
