Metadata-Version: 2.1
Name: cppcheck-codequality
Version: 1.5.0
Summary: Convert a CppCheck XML report to a GitLab-compatible Code Quality JSON report.
Home-page: https://gitlab.com/ahogen/cppcheck-codequality
License: MIT
Author: Alex Hogen
Author-email: code.ahogen@outlook.com
Requires-Python: >=3.7,<3.14
Classifier: Environment :: Console
Classifier: Intended Audience :: Developers
Classifier: License :: OSI Approved :: MIT License
Classifier: Programming Language :: Python :: 3
Classifier: Programming Language :: Python :: 3.7
Classifier: Programming Language :: Python :: 3.8
Classifier: Programming Language :: Python :: 3.9
Classifier: Programming Language :: Python :: 3.10
Classifier: Programming Language :: Python :: 3.11
Classifier: Programming Language :: Python :: 3.12
Classifier: Programming Language :: Python :: 3.13
Classifier: Topic :: Software Development :: Quality Assurance
Classifier: Topic :: Utilities
Requires-Dist: xmltodict (>=0.14.0,<0.15.0)
Project-URL: Bug Tracker, https://gitlab.com/ahogen/cppcheck-codequality/-/issues
Project-URL: Changelog, https://gitlab.com/ahogen/cppcheck-codequality/-/blob/main/CHANGELOG.md
Project-URL: Repository, https://gitlab.com/ahogen/cppcheck-codequality
